{"objects": [{"confidence": 0.6, "alert_tags": [], "bounding_box": [558, 327, 100, 80], "new": false, "times_lost_by_convnet": 54, "tracking_id": 10587, "static": true, "type": "car", "lost": false, "counted": false, "speed": 0.0, "created_at": "2017-12-22 10:28:34.264100"}, {"confidence": 0.58, "alert_tags": [], "bounding_box": [510, 194, 32, 29], "new": false, "times_lost_by_convnet": 0, "tracking_id": 10588, "static": false, "type": "car", "lost": false, "counted": false, "speed": 4.46177555416774, "created_at": "2017-12-22 10:28:40.803648"}, {"confidence": 0.71, "alert_tags": [], "bounding_box": [551, 173, 25, 19], "new": false, "times_lost_by_convnet": 0, "tracking_id": 10590, "static": false, "type": "car", "lost": false, "counted": false, "speed": 2.6120361838087436, "created_at": "2017-12-22 10:28:44.797264"}], "frame_index": 227847}