{"objects": [{"confidence": 0.53, "alert_tags": [], "bounding_box": [246, 385, 42, 36], "new": false, "times_lost_by_convnet": 26, "tracking_id": 10592, "static": false, "type": "car", "lost": false, "counted": false, "speed": 1.7317467645749562, "created_at": "2017-12-22 10:28:47.244379"}, {"confidence": 0.69, "alert_tags": [], "bounding_box": [496, 214, 30, 22], "new": false, "times_lost_by_convnet": 1, "tracking_id": 10596, "static": false, "type": "car", "lost": false, "counted": false, "speed": 4060.6593178890353, "created_at": "2017-12-22 10:28:54.744234"}, {"confidence": 0.67, "alert_tags": [], "bounding_box": [556, 178, 22, 19], "new": false, "times_lost_by_convnet": 0, "tracking_id": 10597, "static": false, "type": "car", "lost": false, "counted": false, "speed": 1.731746770583582, "created_at": "2017-12-22 10:28:55.006382"}, {"confidence": 0.51, "alert_tags": [], "bounding_box": [514, 179, 27, 22], "new": false, "times_lost_by_convnet": 2, "tracking_id": 10598, "static": false, "type": "car", "lost": false, "counted": false, "speed": 5.195240327993857, "created_at": "2017-12-22 10:28:56.653087"}], "frame_index": 229076}