{"objects": [{"confidence": 0.58, "type": "truck", "static": false, "created_at": "2017-12-28 05:04:54.186854", "times_lost_by_convnet": 76, "speed": 0.0, "lost": false, "alert_tags": [], "tracking_id": 24547, "bounding_box": [380, 323, 71, 53], "new": false, "counted": true}, {"confidence": 0.6, "type": "bus", "static": false, "created_at": "2017-12-28 05:05:00.523301", "times_lost_by_convnet": 1, "speed": 0.8795642970767772, "lost": false, "alert_tags": [], "tracking_id": 24548, "bounding_box": [385, 230, 96, 98], "new": false, "counted": false}, {"confidence": 0.65, "type": "car", "static": false, "created_at": "2017-12-28 05:05:00.837473", "times_lost_by_convnet": -1, "speed": 0.8795643185729071, "lost": false, "alert_tags": [], "tracking_id": 24549, "bounding_box": [451, 317, 61, 58], "new": false, "counted": false}, {"confidence": 0.64, "type": "car", "static": false, "created_at": "2017-12-28 05:05:04.087479", "times_lost_by_convnet": 7, "speed": 1.5024343707470336, "lost": false, "alert_tags": [], "tracking_id": 24550, "bounding_box": [494, 290, 49, 38], "new": false, "counted": false}, {"confidence": 0.56, "type": "car", "static": false, "created_at": "2017-12-28 05:05:06.321483", "times_lost_by_convnet": 9, "speed": 5.326358189800393, "lost": false, "alert_tags": [], "tracking_id": 24551, "bounding_box": [476, 226, 41, 41], "new": false, "counted": false}, {"confidence": 0.7, "type": "car", "static": false, "created_at": "2017-12-28 05:05:07.437923", "times_lost_by_convnet": 0, "speed": 20.58518550429361, "lost": false, "alert_tags": [], "tracking_id": 24552, "bounding_box": [546, 224, 35, 28], "new": false, "counted": false}, {"confidence": 0.52, "type": "car", "static": false, "created_at": "2017-12-28 05:05:08.769575", "times_lost_by_convnet": 7, "speed": 7.6304577898858446, "lost": false, "alert_tags": [], "tracking_id": 24553, "bounding_box": [509, 213, 28, 29], "new": false, "counted": false}], "frame_index": 5471087}