{"objects": [{"confidence": 0.57, "type": "bus", "static": true, "created_at": "2017-12-28 05:05:00.523301", "times_lost_by_convnet": 1, "speed": 1.9834333480710542, "lost": false, "alert_tags": [], "tracking_id": 24548, "bounding_box": [387, 231, 95, 97], "new": false, "counted": false}, {"confidence": 0.74, "type": "car", "static": true, "created_at": "2017-12-28 05:05:00.837473", "times_lost_by_convnet": -1, "speed": 3.3880152434116635, "lost": false, "alert_tags": [], "tracking_id": 24549, "bounding_box": [449, 318, 63, 56], "new": false, "counted": false}, {"confidence": 0.56, "type": "car", "static": false, "created_at": "2017-12-28 05:05:08.769575", "times_lost_by_convnet": 0, "speed": 18.843691014393563, "lost": false, "alert_tags": [], "tracking_id": 24553, "bounding_box": [504, 218, 27, 32], "new": false, "counted": false}], "frame_index": 5472135}