{"objects": [{"confidence": 0.57, "type": "bus", "static": true, "created_at": "2017-12-28 05:05:00.523301", "times_lost_by_convnet": 0, "speed": 5.941323069426347, "lost": false, "alert_tags": [], "tracking_id": 24548, "bounding_box": [381, 214, 118, 142], "new": false, "counted": false}, {"confidence": 0.75, "type": "car", "static": true, "created_at": "2017-12-28 05:05:00.837473", "times_lost_by_convnet": 0, "speed": 3.382903878669115, "lost": false, "alert_tags": [], "tracking_id": 24549, "bounding_box": [456, 319, 58, 52], "new": false, "counted": false}, {"confidence": 0.59, "type": "car", "static": true, "created_at": "2017-12-28 05:05:08.769575", "times_lost_by_convnet": 1, "speed": 3.960882001495983, "lost": false, "alert_tags": [], "tracking_id": 24553, "bounding_box": [499, 220, 27, 36], "new": false, "counted": false}], "frame_index": 5472663}